gqlalchemy/__init__.py
gqlalchemy/connection.py
gqlalchemy/disk_storage.py
gqlalchemy/exceptions.py
gqlalchemy/graph_algorithms/__init__.py
gqlalchemy/graph_algorithms/integrated_algorithms.py
gqlalchemy/graph_algorithms/query_builder.py
gqlalchemy/graph_algorithms/query_modules.py
gqlalchemy/instance_runner.py
gqlalchemy/memgraph_constants.py
gqlalchemy/models.py
gqlalchemy/query_builders/__init__.py
gqlalchemy/query_builders/declarative_base.py
gqlalchemy/query_builders/memgraph_query_builder.py
gqlalchemy/query_builders/neo4j_query_builder.py
gqlalchemy/query_modules/__init__.py
gqlalchemy/query_modules/push_streams/kafka.py
gqlalchemy/query_modules/push_streams/power_bi.py
gqlalchemy/transformations/__init__.py
gqlalchemy/transformations/constants.py
gqlalchemy/transformations/export/__init__.py
gqlalchemy/transformations/export/graph_transporter.py
gqlalchemy/transformations/export/transporter.py
gqlalchemy/transformations/graph_type.py
gqlalchemy/transformations/importing/__init__.py
gqlalchemy/transformations/importing/graph_importer.py
gqlalchemy/transformations/importing/importer.py
gqlalchemy/transformations/importing/loaders.py
gqlalchemy/transformations/translators/__init__.py
gqlalchemy/transformations/translators/dgl_translator.py
gqlalchemy/transformations/translators/nx_translator.py
gqlalchemy/transformations/translators/pyg_translator.py
gqlalchemy/transformations/translators/translator.py
gqlalchemy/utilities.py
gqlalchemy/vendors/__init__.py
gqlalchemy/vendors/database_client.py
gqlalchemy/vendors/memgraph.py
gqlalchemy/vendors/neo4j.py
gqlalchemy_tailor-1.4.1.dist-info/LICENSE
gqlalchemy_tailor-1.4.1.dist-info/WHEEL
gqlalchemy_tailor-1.4.1.dist-info/METADATA
gqlalchemy_tailor-1.4.1.dist-info/RECORD
