Metadata-Version: 2.1
Name: gqlalchemy-tailor
Version: 1.4.1
Summary: GQLAlchemy is a library developed to assist with writing and running queries in Memgraph. Upgraded networkx to 3.1.0.
Home-page: https://github.com/memgraph/gqlalchemy
License: Apache-2.0
Author: Bruno Sacaric
Author-email: bruno.sacaric@memgraph.com
Requires-Python: >=3.8,<4.0
Classifier: License :: OSI Approved :: Apache Software License
Classifier: Programming Language :: Python :: 3
Classifier: Programming Language :: Python :: 3.8
Classifier: Programming Language :: Python :: 3.9
Classifier: Programming Language :: Python :: 3.10
Classifier: Programming Language :: Python :: 3.11
Provides-Extra: all
Provides-Extra: arrow
Provides-Extra: dgl
Provides-Extra: torch-pyg
Requires-Dist: adlfs (>=2022.2.0,<2023.0.0)
Requires-Dist: dacite (>=1.6.0,<2.0.0)
Requires-Dist: dgl (>=0.9.1,<0.10.0) ; extra == "dgl" or extra == "all"
Requires-Dist: docker (>=5.0.3,<6.0.0)
Requires-Dist: neo4j (>=4.4.3,<5.0.0)
Requires-Dist: networkx (==3.1)
Requires-Dist: numpy (>=1.24.1,<2.0.0)
Requires-Dist: platformdirs (==3.8.0)
Requires-Dist: psutil (>=5.9.0,<6.0.0)
Requires-Dist: pyarrow (>=9.0.0,<10.0.0) ; extra == "arrow" or extra == "all"
Requires-Dist: pydantic (>=1.8.2,<2.0.0)
Requires-Dist: pymgclient (==1.3.1)
Requires-Dist: torch (>=1.13.1,<2.0.0) ; extra == "dgl" or extra == "all" or extra == "torch-pyg"
Project-URL: Repository, https://github.com/memgraph/gqlalchemy
